pylwl/__init__.py
pylwl/models/__init__.py
pylwl/models/base_model.py
pylwl/models/classic_lw.py
pylwl/models/gd_lw.py
pylwl/shared/__init__.py
pylwl/shared/data_preparer.py
pylwl/shared/kernel.py
pylwl/shared/scaler.py
pylwl/shared/scorer.py
pylwl/shared/verifier.py
pylwl-0.2.0.dist-info/licenses/LICENSE
pylwl-0.2.0.dist-info/METADATA
pylwl-0.2.0.dist-info/WHEEL
pylwl-0.2.0.dist-info/top_level.txt
pylwl-0.2.0.dist-info/RECORD
